MANIFEST.in
README.md
setup.py
bod_metadata_management/__init__.py
bod_metadata_management.egg-info/PKG-INFO
bod_metadata_management.egg-info/SOURCES.txt
bod_metadata_management.egg-info/dependency_links.txt
bod_metadata_management.egg-info/not-zip-safe
bod_metadata_management.egg-info/requires.txt
bod_metadata_management.egg-info/top_level.txt