Metadata-Version: 1.0
Name: bod-metadata-management
Version: 0.2
Summary: modules, libraries, and scripts to manage metadata for Boston Open Data
Home-page: https://github.com/vmanamino/bod_metadata_management
Author: Viral Amin
Author-email: vmanamino@gmail.com
License: MIT
Platform: UNKNOWN
